bosanski_kalkulator/__init__.py
bosanski_kalkulator/main.py
bosanski_kalkulator/audio/bosanska_artiljerija.mp3
bosanski_kalkulator/audio/pucnjava.mp3
bosanski_kalkulator/images/zastava_bosne_i_hercegovine.png
bosanski_kalkulator-0.1.2.dist-info/LICENSE
bosanski_kalkulator-0.1.2.dist-info/METADATA
bosanski_kalkulator-0.1.2.dist-info/WHEEL
bosanski_kalkulator-0.1.2.dist-info/entry_points.txt
bosanski_kalkulator-0.1.2.dist-info/top_level.txt
bosanski_kalkulator-0.1.2.dist-info/RECORD
