Metadata-Version: 2.1
Name: bosanski-kalkulator
Version: 0.1.2
Summary: najbolji kalkulator
Home-page: https://github.com/ona-li-toki-e-jan-Epiphany-tawa-mi/Bosanski-Kalkulator
Download-URL: https://github.com/ona-li-toki-e-jan-Epiphany-tawa-mi/Bosanski-Kalkulator/releases
Author: ona li toki e jan Epiphany tawa mi
License: MIT
Keywords: Bosanski Kalkulator,calculator,kalkulator,bosnian,bosnia,bosna,bosanski
Platform: Windows
Platform: POSIX
Platform: MacOS
Classifier: Intended Audience :: End Users/Desktop
Classifier: License :: OSI Approved :: MIT License
Classifier: Operating System :: MacOS
Classifier: Operating System :: Microsoft :: Windows
Classifier: Operating System :: POSIX
Classifier: Programming Language :: Python :: 3
Classifier: Topic :: Artistic Software
Classifier: Topic :: Utilities
License-File: LICENSE
Requires-Dist: PySimpleGUI
Requires-Dist: playsound
